plots_maps/__init__.py
plots_maps/plots_maps.py
pyplotsmaps-0.0.2.dist-info/DESCRIPTION.rst
pyplotsmaps-0.0.2.dist-info/METADATA
pyplotsmaps-0.0.2.dist-info/RECORD
pyplotsmaps-0.0.2.dist-info/WHEEL
pyplotsmaps-0.0.2.dist-info/metadata.json
pyplotsmaps-0.0.2.dist-info/top_level.txt
