Metadata-Version: 2.0
Name: pyplotsmaps
Version: 0.0.2
Summary: A python package for iot projects to plot and locate
Home-page: https://github.com/dazzHere/PY-PLOTS-MAPS
Author: dazzHere
Author-email: dhanushdazz@gmail.com
License: UNKNOWN
Keywords: iot,iot-plots,maps,maps-iot,plots
Platform: UNKNOWN
Classifier: Programming Language :: Python :: 3
Classifier: Programming Language :: Python :: 2
Classifier: Operating System :: OS Independent
Requires-Dist: requests
